Metadata-Version: 1.0
Name: distribution-jvn
Version: 0.1
Summary: Gaussian and Boolean distributions
Home-page: UNKNOWN
Author: UNKNOWN
Author-email: UNKNOWN
License: UNKNOWN
Platform: UNKNOWN
